{
  "http://www.sdmone.pro": {
    "node_count": 1,
    "sub_url": "https://c.sdm.lat/link/AxLkxsrgvCgnQZXO?sub=3",
    "email": "k0juc0751yci@qq.com",
    "expire_info": "2026-02-24 12:19:23+08:00"
  },
  "https://a.sdmone.pro": {
    "node_count": 1,
    "sub_url": "https://c.sdm.lat/link/zdMZB6IBSjBNKEyi?sub=3",
    "email": "2uo8gsax7x98@outlook.com",
    "expire_info": "2026-02-24 12:19:49+08:00"
  },
  "https://3fanduijie.xyz": {
    "node_count": 2,
    "sub_url": "https://3fanduijie.xyz/api/v1/client/subscribe?token=7ded444779cbf49804bd4984e2bfad22",
    "email": "gyi5ungf29yu@gmail.com",
    "expire_info": "1970-01-01 08:00:00+08:00"
  },
  "https://best.nxxbbf.com": {
    "node_count": 9,
    "sub_url": "https://bestti.whtjdasha.com/api/v1/client/subscribe?token=ea2f99b5c5a28542fc32ab2fe2c15bf6",
    "email": "8zt5szulnnwq@qq.com",
    "expire_info": "2026-02-23 14:20:28+08:00"
  },
  "https://durex001.ggff.net": {
    "node_count": 3,
    "sub_url": "https://subscribe001.ggff.net/subscribe/e3b4d1a1eee90f837477b445877ef29c",
    "email": "v0ahz8mrnsjb@gmail.com",
    "expire_info": "2026-03-25 12:21:01+08:00"
  },
  "https://mgnet.vip": {
    "node_count": 11,
    "sub_url": "https://aa.mgnet.sbs/link/LuJ7joLFboha93Rz?sub=3",
    "email": "jucj2eb9x48z@qq.com",
    "expire_info": "2026-02-25 13:23:06+08:00"
  },
  "https://multiserver.multiserveradelshoop.com": {
    "node_count": 2,
    "sub_url": "https://multiserver.multiserveradelshoop.com/api/v1/client/subscribe?token=867b35253f867f225dac0911b11a61bf",
    "email": "1bls4t8dqggf@outlook.com",
    "expire_info": "永不过期"
  },
  "https://sdmone.pro": {
    "node_count": 1,
    "sub_url": "https://c.sdm.lat/link/jxhRSOsyljT3L7Vi?sub=3",
    "email": "xb8gz77u4f3z@gmail.com",
    "expire_info": "2026-02-24 12:23:42+08:00"
  },
  "https://slianvpn.com": {
    "node_count": 50,
    "sub_url": "https://slvp.nxxbbf.com/api/v1/client/subscribe?token=9f32842607ddd4a7aac47a9f4f4a703e",
    "email": "7ueigsmtpyok@outlook.com",
    "expire_info": "2026-02-23 14:23:52+08:00"
  },
  "https://tizi.bulehu.com": {
    "node_count": 1,
    "sub_url": "https://tizi.bulehu.com/api/v1/client/subscribe?token=ce97d195b5d731317be6b56ad0b09bf8",
    "email": "3etzngfenias@qq.com",
    "expire_info": "2026-02-24 12:24:12+08:00"
  },
  "https://xbd.iftballs.com": {
    "node_count": 3,
    "sub_url": "https://xbd.iftballs.com/api/v1/client/subscribe?token=2e474ab96919643ffd6175168e0af572",
    "email": "hcyhb8oc8z9o@outlook.com",
    "expire_info": "永不过期"
  },
  "https://yywhale.com": {
    "node_count": 5,
    "sub_url": "https://www.yywhale.com/api/v1/client/subscribe?token=d386694b57d4a2b2db8ea2a51a7f59f1",
    "email": "nljt3wyfntcj@gmail.com",
    "expire_info": "2026-02-23 13:28:29+08:00"
  }
}