{
  "https://3fanduijie.xyz": {
    "node_count": 2,
    "sub_url": "https://3fanduijie.xyz/api/v1/client/subscribe?token=1d1748a5f830f8332fd5f9579d3876ca",
    "email": "nhftuf8qn2e1@qq.com",
    "expire_info": "1970-01-01 08:00:00+08:00"
  },
  "https://a.sdmone.pro": {
    "node_count": 1,
    "sub_url": "https://c.sdm.lat/link/Jj4rnSmnelWOO5Me?sub=3",
    "email": "wmsf16znct6s@gmail.com",
    "expire_info": "2026-01-08 11:32:44+08:00"
  },
  "https://fastvpn.top": {
    "node_count": 1,
    "sub_url": "https://fastvpn.top/s/76a6f00987a70f56b062a02effd86c06",
    "email": "kqe9vdv2ver8@qq.com",
    "expire_info": "2026-01-08 11:34:59+08:00"
  },
  "https://go.yueyun.de": {
    "node_count": 30,
    "sub_url": "https://go.yueyun.de/api/v1/client/subscribe?token=84db316a12fd4f79f2543f476a6e9585",
    "email": "qgvrhschachu@outlook.com",
    "expire_info": "2026-01-08 11:36:12+08:00"
  },
  "https://best.nxxbbf.com": {
    "node_count": 9,
    "sub_url": "https://bestti.whtjdasha.com/api/v1/client/subscribe?token=12b01bf6a83200d77b8a573a4232431c",
    "email": "wx3f5jmpgl7i@qq.com",
    "expire_info": "2026-01-06 13:05:55+08:00"
  },
  "https://mgnet.vip": {
    "node_count": 11,
    "sub_url": "https://aa.mgnet.sbs/link/PCdNNc1n7TltN6qw?sub=3",
    "email": "ay4tsno3n49t@outlook.com",
    "expire_info": "2026-01-09 12:38:25+08:00"
  },
  "https://multiserver.multiserveradelshoop.com": {
    "node_count": 2,
    "sub_url": "https://multiserver.multiserveradelshoop.com/api/v1/client/subscribe?token=80706738cea0365341ab94fb30d58892",
    "email": "jcjiw05o58qr@gmail.com",
    "expire_info": "永不过期"
  },
  "https://sdmone.pro": {
    "node_count": 1,
    "sub_url": "https://c.sdm.lat/link/zg9o6cftOS8tNWuz?sub=3",
    "email": "ievbv7npwjre@gmail.com",
    "expire_info": "2026-01-08 11:39:13+08:00"
  },
  "https://vn3765.cc": {
    "node_count": 5,
    "sub_url": "https://vn3765.cc/s/0679ba0f5beafc613d9f6fe220f4659a",
    "email": "sc5ytapadnpd@qq.com",
    "expire_info": "2026-01-07 13:41:00+08:00"
  },
  "https://slianvpn.com": {
    "node_count": 50,
    "sub_url": "https://slianvpn.com/api/v1/client/subscribe?token=3df6f882b5890ee26d11f30b6a6d516c",
    "email": "ul7yu8jphl91@qq.com",
    "expire_info": "2026-01-07 13:39:23+08:00"
  },
  "https://xbd.iftballs.com": {
    "node_count": 3,
    "sub_url": "https://xbd.iftballs.com/api/v1/client/subscribe?token=b46e0b543209b0a54a7db5f9a0305c78",
    "email": "286s8759i4gu@qq.com",
    "expire_info": "永不过期"
  },
  "https://xstar8888.com": {
    "node_count": 12,
    "sub_url": "https://xstar8888.com/api/v1/client/subscribe?token=accd608c611a2ec89b7d201d24c39627",
    "email": "yrzjlya2wkn1@qq.com",
    "expire_info": "2026-01-10 11:45:13+08:00"
  },
  "https://yywhale.com": {
    "node_count": 5,
    "sub_url": "https://www.yywhale.com/api/v1/client/subscribe?token=e432c8d065f8ede0ee20878b0dde6d14",
    "email": "c040r9lhfmub@qq.com",
    "expire_info": "2026-01-07 12:46:50+08:00"
  }
}