{
  "http://www.sdmone.pro": {
    "node_count": 1,
    "sub_url": "https://c.sdm.lat/link/uIKEzcA9UHt9Tlri?sub=3",
    "email": "df8esa9g3m92@qq.com",
    "expire_info": "2025-11-15 02:30:23+08:00"
  },
  "https://a.sdmone.pro": {
    "node_count": 1,
    "sub_url": "https://c.sdm.lat/link/BnWXBPO4qeriZePW?sub=3",
    "email": "ovgg2k906rl8@gmail.com",
    "expire_info": "2025-11-15 02:30:58+08:00"
  },
  "https://cfvpn.com": {
    "node_count": 36,
    "sub_url": "http://cfvpn.com/api/v1/client/subscribe?token=288b58758c0aba4271cd4ffcd3f9bf1b",
    "email": "p446yglod5nz@gmail.com",
    "expire_info": "2025-11-14 03:32:02+08:00"
  },
  "https://fastvpn.top": {
    "node_count": 35,
    "sub_url": "https://fastvpn.top/s/cc19d75fd95266e5971aca80b154dcbc",
    "email": "kheiqtsqu6d7@outlook.com",
    "expire_info": "2025-11-15 02:32:52+08:00"
  },
  "https://go.yueyun.de": {
    "node_count": 30,
    "sub_url": "https://go.yueyun.de/api/v1/client/subscribe?token=46810299f51f16c61b0282124c11798d",
    "email": "l2x9w4vprlhb@gmail.com",
    "expire_info": "2025-11-15 02:33:35+08:00"
  },
  "https://gods1.dashicn.buzz": {
    "node_count": 24,
    "sub_url": "https://dftyfdf1j00ll.dashuai.us/api/v1/client/subscribe?token=799bf3ec9a19996691c619318ec26e3f",
    "email": "dwad3m39141j@qq.com",
    "expire_info": "2025-11-14 06:33:38+08:00"
  },
  "https://gods2.dashicn.buzz": {
    "node_count": 24,
    "sub_url": "https://dftyfdf1j00ll.dashuai.us/api/v1/client/subscribe?token=fb7292246a946649694c140fd6b39788",
    "email": "boacwbor70sf@outlook.com",
    "expire_info": "2025-11-14 06:33:38+08:00"
  },
  "https://gods3.dashicn.buzz": {
    "node_count": 24,
    "sub_url": "https://dftyfdf1j00ll.dashuai.us/api/v1/client/subscribe?token=f75d57a60eb3e105adfedb6d817debd1",
    "email": "93bbtp45v599@gmail.com",
    "expire_info": "2025-11-14 06:33:38+08:00"
  },
  "https://mgnet.vip": {
    "node_count": 11,
    "sub_url": "https://aa.mgnet.sbs/link/h1sNoamTo4TQ6xUN?sub=3",
    "email": "672q7acx6ozd@gmail.com",
    "expire_info": "2025-11-16 03:35:54+08:00"
  },
  "https://multiserver.multiserveradelshoop.com": {
    "node_count": 2,
    "sub_url": "https://multiserver.multiserveradelshoop.com/api/v1/client/subscribe?token=e5dae36ce5c52ce3823b1cade225b770",
    "email": "7tg3doq4yarf@outlook.com",
    "expire_info": "永不过期"
  },
  "https://sdmone.pro": {
    "node_count": 1,
    "sub_url": "https://c.sdm.lat/link/l5blQs1hEpDNlDGJ?sub=3",
    "email": "fhypuu2fiimx@outlook.com",
    "expire_info": "2025-11-15 02:37:11+08:00"
  },
  "https://slian.slianvpn.top": {
    "node_count": 50,
    "sub_url": "https://slvp.nxxbbf.com/api/v1/client/subscribe?token=c50d90795f83ab7056eb38a5b1f73721",
    "email": "zzwnjx1xba3m@qq.com",
    "expire_info": "2025-11-14 04:37:20+08:00"
  },
  "https://slianvpn.com": {
    "node_count": 50,
    "sub_url": "https://slurl.izenny.com/api/v1/client/subscribe?token=34d5e012026411fff997499955b7b451",
    "email": "8fm85sqdp42c@outlook.com",
    "expire_info": "2025-11-14 04:37:20+08:00"
  },
  "https://slianvpn.top": {
    "node_count": 50,
    "sub_url": "https://slvp.nxxbbf.com/api/v1/client/subscribe?token=7995915f0444c3ef433d0648506f933b",
    "email": "m5fenlkpzh3b@gmail.com",
    "expire_info": "2025-11-14 04:37:21+08:00"
  },
  "https://vfentou.com": {
    "node_count": 2,
    "sub_url": "https://lailainnn.tiankongzhicheng.online/link/9N0bG0nKYnx4cvr1?sub=3",
    "email": "dzjn3xl6aa4i@qq.com",
    "expire_info": "2025-11-15 02:38:22+08:00"
  },
  "https://www.xinyun.buzz": {
    "node_count": 26,
    "sub_url": "https://tbsss.xn--xhqy01cv5qjky.com/link/5Q9Mh0TRfc7G0Jbn?sub=3",
    "email": "euce4kd5ez4g@outlook.com",
    "expire_info": "2025-11-15 02:12:37+08:00"
  },
  "https://xbd.iftballs.com": {
    "node_count": 3,
    "sub_url": "https://xbd.iftballs.com/api/v1/client/subscribe?token=2554421a66de25a41f868e791d9b7318",
    "email": "sbl5s3d12a9d@outlook.com",
    "expire_info": "永不过期"
  },
  "https://yywhale.com": {
    "node_count": 5,
    "sub_url": "https://www.yywhale.com/api/v1/client/subscribe?token=7e2502f5d7e827b92b63da39fd591d84",
    "email": "hdugd600gn08@gmail.com",
    "expire_info": "2025-11-14 03:40:46+08:00"
  }
}