{
  "http://dingyue.xjay.xyz": {
    "node_count": 7,
    "sub_url": "https://dingyue.xjay.xyz/api/v1/client/subscribe?token=6635dfa7c570eb54255fcdc237b5f8d2",
    "email": "9nyr8ly5ptto@qq.com",
    "expire_info": "2025-11-10 23:23:25+08:00"
  },
  "http://www.sdmone.pro": {
    "node_count": 1,
    "sub_url": "https://c.sdm.lat/link/sLyAMaNljKdXiY66?sub=3",
    "email": "9whmk85hjyrn@qq.com",
    "expire_info": "2025-11-11 22:23:37+08:00"
  },
  "https://a.sdmone.pro": {
    "node_count": 1,
    "sub_url": "https://c.sdm.lat/link/49DdUyzEjVx3ahWW?sub=3",
    "email": "wih4tde4sicp@outlook.com",
    "expire_info": "2025-11-11 22:24:18+08:00"
  },
  "https://best.nxxbbf.com": {
    "node_count": 9,
    "sub_url": "https://bestti.whtjdasha.com/api/v1/client/subscribe?token=55ead05e3138cc8b478f9564fe503a5c",
    "email": "8rqxwlicjycf@outlook.com",
    "expire_info": "2025-11-09 23:58:06+08:00"
  },
  "https://cfvpn.com": {
    "node_count": 36,
    "sub_url": "http://cfvpn.com/api/v1/client/subscribe?token=21d9cf8c627c5dbc25b51d4fd828bba4",
    "email": "vnsr3gi60o1a@qq.com",
    "expire_info": "2025-11-10 23:25:47+08:00"
  },
  "https://go.yueyun.de": {
    "node_count": 30,
    "sub_url": "https://go.yueyun.de/api/v1/client/subscribe?token=3f510b1098e7bc6fd39cc48194cc1c92",
    "email": "jet4awg2afs0@qq.com",
    "expire_info": "2025-11-11 22:27:40+08:00"
  },
  "https://gods3.dashicn.buzz": {
    "node_count": 24,
    "sub_url": "https://dftyfdf1j00ll.dashuai.us/api/v1/client/subscribe?token=835e99e50c80031e51844f35c826ed76",
    "email": "augy71mlq8u6@qq.com",
    "expire_info": "2025-11-11 02:27:44+08:00"
  },
  "https://gods1.dashicn.buzz": {
    "node_count": 24,
    "sub_url": "https://dftyfdf1j00ll.dashuai.us/api/v1/client/subscribe?token=ad765a434c4ec7d421a893e65536be31",
    "email": "appqvzf4tmis@qq.com",
    "expire_info": "2025-11-11 02:27:43+08:00"
  },
  "https://gods2.dashicn.buzz": {
    "node_count": 24,
    "sub_url": "https://dftyfdf1j00ll.dashuai.us/api/v1/client/subscribe?token=4ed0400bdd960f2a274f5202ef5c17c1",
    "email": "tojgshh2nwku@qq.com",
    "expire_info": "2025-11-11 02:27:44+08:00"
  },
  "https://mgnet.vip": {
    "node_count": 11,
    "sub_url": "https://aa.mgnet.sbs/link/0oH5VxCvhqGsLewb?sub=3",
    "email": "ezqag3zhdhnt@outlook.com",
    "expire_info": "2025-11-12 23:30:14+08:00"
  },
  "https://multiserver.multiserveradelshoop.com": {
    "node_count": 2,
    "sub_url": "https://multiserver.multiserveradelshoop.com/api/v1/client/subscribe?token=717b97f2e0efd6dd8d235fc0550eaaf5",
    "email": "nbx5kmuey8ov@qq.com",
    "expire_info": "永不过期"
  },
  "https://sdmone.pro": {
    "node_count": 1,
    "sub_url": "https://c.sdm.lat/link/euId4oKrfMqHB8IT?sub=3",
    "email": "sm5geydmvp57@outlook.com",
    "expire_info": "2025-11-11 22:31:23+08:00"
  },
  "https://slianvpn.top": {
    "node_count": 50,
    "sub_url": "https://slianvpn.top/api/v1/client/subscribe?token=b8cf83f4cb0dfa75795f0bab3c40165b",
    "email": "qfh2e0xqhqmh@gmail.com",
    "expire_info": "2025-11-11 00:31:33+08:00"
  },
  "https://slianvpn.com": {
    "node_count": 50,
    "sub_url": "https://slianvpn.com/api/v1/client/subscribe?token=f9caeaf9195033711bd1c60e52d8b169",
    "email": "ouqlutvb5sho@gmail.com",
    "expire_info": "2025-11-11 00:31:32+08:00"
  },
  "https://slian.slianvpn.top": {
    "node_count": 50,
    "sub_url": "https://slian.slianvpn.top/api/v1/client/subscribe?token=048d948c973f1cffccefa28ad7f884cf",
    "email": "up3hryu890i5@gmail.com",
    "expire_info": "2025-11-11 00:31:32+08:00"
  },
  "https://tudoujiasu17.com": {
    "node_count": 34,
    "sub_url": "https://sub.tudou106.xyz/api/v1/client/subscribe?token=f5ebe2c9c6ac015b1e6f9b71e2825c4b",
    "email": "quy899kejzc1@outlook.com",
    "expire_info": "2025-11-10 23:32:32+08:00"
  },
  "https://vfentou.com": {
    "node_count": 2,
    "sub_url": "https://lailainnn.tiankongzhicheng.online/link/QZahcxUGPc8DZwCG?sub=3",
    "email": "cmfh94bjp5tg@outlook.com",
    "expire_info": "2025-11-11 22:33:00+08:00"
  },
  "https://yywhale.com": {
    "node_count": 5,
    "sub_url": "https://www.yywhale.com/api/v1/client/subscribe?token=254551763c06650bbe2fa84728f44d04",
    "email": "nxgdgby9u8dd@qq.com",
    "expire_info": "2025-11-10 23:35:59+08:00"
  }
}